LICENSE
MANIFEST.in
README.rst
setup.cfg
setup.py
hangups/__init__.py
hangups/auth.py
hangups/channel.py
hangups/client.py
hangups/conversation.py
hangups/conversation_event.py
hangups/event.py
hangups/exceptions.py
hangups/hangouts_pb2.py
hangups/http_utils.py
hangups/message_parser.py
hangups/parsers.py
hangups/pblite.py
hangups/user.py
hangups/version.py
hangups.egg-info/PKG-INFO
hangups.egg-info/SOURCES.txt
hangups.egg-info/dependency_links.txt
hangups.egg-info/entry_points.txt
hangups.egg-info/requires.txt
hangups.egg-info/top_level.txt
hangups/test/__init__.py
hangups/test/test_auth.py
hangups/test/test_channel.py
hangups/test/test_emoticon.py
hangups/test/test_event.py
hangups/test/test_message_parser.py
hangups/test/test_notifier.py
hangups/test/test_pblite.proto
hangups/test/test_pblite.py
hangups/test/test_pblite_pb2.py
hangups/test/test_user.py
hangups/ui/__init__.py
hangups/ui/__main__.py
hangups/ui/emoticon.py
hangups/ui/notifier.py
hangups/ui/utils.py